lithoxyl/__init__.py
lithoxyl/_syslog_emitter.py
lithoxyl/accumulators.py
lithoxyl/action.py
lithoxyl/actors.py
lithoxyl/common.py
lithoxyl/context.py
lithoxyl/emitters.py
lithoxyl/ewma.py
lithoxyl/logger.py
lithoxyl/moment.py
lithoxyl/p_squared.py
lithoxyl/quantile.py
lithoxyl/sensible.py
lithoxyl/sinks.py
lithoxyl/utils.py
lithoxyl/tests/__init__.py
lithoxyl/tests/_statsutils.py
lithoxyl/tests/test_basic.py
lithoxyl/tests/test_context.py
lithoxyl/tests/test_counter_sink.py
lithoxyl/tests/test_formatters.py
lithoxyl/tests/test_levels.py
lithoxyl/tests/test_logger.py
lithoxyl/tests/test_rate_sink.py
lithoxyl/tests/test_sinks.py
lithoxyl/tests/test_stats.py
lithoxyl/tests/test_wrap_all.py
lithoxyl-21.0.0.dist-info/METADATA
lithoxyl-21.0.0.dist-info/WHEEL
lithoxyl-21.0.0.dist-info/pbr.json
lithoxyl-21.0.0.dist-info/top_level.txt
lithoxyl-21.0.0.dist-info/RECORD
