Metadata-Version: 2.1
Name: lithoxyl
Version: 21.0.0
Summary: A systematic approach to logging, profiling, and statisticscollection. Very lightweight, very Pythonic.
Home-page: https://github.com/mahmoud/lithoxyl
Author: Mahmoud Hashemi
Author-email: mahmoud@hatnote.com
License: BSD
Platform: any
Classifier: Intended Audience :: Developers
Classifier: Topic :: System :: Logging
Classifier: Topic :: Utilities
Classifier: Topic :: Software Development :: Libraries :: Application Frameworks
Classifier: License :: OSI Approved :: BSD License
Classifier: Programming Language :: Python :: 2.7
Classifier: Programming Language :: Python :: 3.5
Classifier: Programming Language :: Python :: 3.6
Classifier: Programming Language :: Python :: 3.7
Classifier: Programming Language :: Python :: Implementation :: CPython
Classifier: Programming Language :: Python :: Implementation :: PyPy
Requires-Dist: boltons (>=20.0.0)
